aio_sf/__init__.py
aio_sf/api/__init__.py
aio_sf/api/client.py
aio_sf/api/types.py
aio_sf/api/auth/__init__.py
aio_sf/api/auth/base.py
aio_sf/api/auth/client_credentials.py
aio_sf/api/auth/refresh_token.py
aio_sf/api/auth/sfdx_cli.py
aio_sf/api/auth/static_token.py
aio_sf/api/bulk_v2/__init__.py
aio_sf/api/bulk_v2/client.py
aio_sf/api/bulk_v2/types.py
aio_sf/api/collections/__init__.py
aio_sf/api/collections/batch.py
aio_sf/api/collections/client.py
aio_sf/api/collections/records.py
aio_sf/api/collections/retry.py
aio_sf/api/collections/types.py
aio_sf/api/describe/__init__.py
aio_sf/api/describe/client.py
aio_sf/api/describe/types.py
aio_sf/api/query/__init__.py
aio_sf/api/query/client.py
aio_sf/api/query/types.py
aio_sf/exporter/__init__.py
aio_sf/exporter/bulk_export.py
aio_sf/exporter/parquet_writer.py
aio_sf-0.1.0b11.dist-info/METADATA
aio_sf-0.1.0b11.dist-info/WHEEL
aio_sf-0.1.0b11.dist-info/licenses/LICENSE
aio_sf-0.1.0b11.dist-info/RECORD
