Metadata-Version: 2.4
Name: aio-sf
Version: 0.1.0b11
Summary: Async Salesforce library for Python
Project-URL: Homepage, https://github.com/callawaycloud/aio-salesforce
Project-URL: Repository, https://github.com/callawaycloud/aio-salesforce
Project-URL: Issues, https://github.com/callawaycloud/aio-salesforce/issues
Author-email: Jonas <charlie@callaway.cloud>
License: MIT License
License-File: LICENSE
Classifier: Development Status :: 3 - Alpha
Classifier: Intended Audience :: Developers
Classifier: License :: OSI Approved :: MIT License
Classifier: Programming Language :: Python :: 3
Classifier: Programming Language :: Python :: 3.11
Classifier: Programming Language :: Python :: 3.12
Requires-Python: >=3.11
Requires-Dist: boto3>=1.34.0
Requires-Dist: httpx>=0.25.0
Requires-Dist: pandas>=2.0.0
Requires-Dist: pyarrow>=10.0.0
Requires-Dist: pydantic>=2.0.0
Requires-Dist: python-dotenv>=1.0.0
Provides-Extra: core
Requires-Dist: httpx>=0.25.0; extra == 'core'
Requires-Dist: pydantic>=2.0.0; extra == 'core'
Requires-Dist: python-dotenv>=1.0.0; extra == 'core'
Provides-Extra: dev
Requires-Dist: black>=23.0.0; extra == 'dev'
Requires-Dist: mypy>=1.5.0; extra == 'dev'
Requires-Dist: pre-commit>=3.0.0; extra == 'dev'
Requires-Dist: pytest-asyncio>=0.21.0; extra == 'dev'
Requires-Dist: pytest-cov>=4.0.0; extra == 'dev'
Requires-Dist: pytest-mock>=3.10.0; extra == 'dev'
Requires-Dist: pytest>=7.0.0; extra == 'dev'
Requires-Dist: ruff>=0.1.0; extra == 'dev'
Requires-Dist: types-requests>=2.31.0; extra == 'dev'
Provides-Extra: exporter
Requires-Dist: boto3>=1.34.0; extra == 'exporter'
Requires-Dist: pandas>=2.0.0; extra == 'exporter'
Requires-Dist: pyarrow>=10.0.0; extra == 'exporter'
